LICENSE
setup.py
data/__init__.py
data/xml/XMLNode.py
data/xml/XMLParser.py
data/xml/XMLPath.py
data/xml/XMLTree.py
data/xml/__init__.py
pyecosystem.egg-info/PKG-INFO
pyecosystem.egg-info/SOURCES.txt
pyecosystem.egg-info/dependency_links.txt
pyecosystem.egg-info/requires.txt
pyecosystem.egg-info/top_level.txt
workflow/Errors.py
workflow/Executable.py
workflow/Step.py
workflow/Workflow.py
workflow/__init__.py